{"paths":{"2":["Notice/Agree",0],"3":["Notice/Notice",0],"5":["Home/NanView",0],"6":["Help/HelpViewItem",0],"10":["End/EndView",0],"11":["Record/RecordItem",0],"12":["Help/HelpView",0],"13":["End/EndView1",0],"14":["End/EndView2",0],"18":["End/EndItem",0],"19":["Record/RecordView",0]},"types":["cc.Prefab"],"uuids":["24s4NJhD1Bhps2+yX8hZV7","29gjCvT9FIu6rMQElZw9nC","448bnOgi1HTJ7oyhscTabJ","60fl4lvrNKurmUKFx4iG0Y","61cyPdEfRN047sDK9rO0W5","63MHNiZX1N2Yj6M3X5Spdp","667lWDFHpD0LVXqBQGBUmn","7bQDsxYiZFM69MU/yVzAMA","8ajU/z94hGeK94WPWXWmoQ","8f5KFHZjZHO4YuAj4RznK/","9cJOkpv+RGFIPo4sXhHlye","adnFi+F49LKI7pGeimnEwR","b83rvG+5hBdIbhpArnmt3K","ceHdLnwelF2r+ykvK7A7xF","d1so97oPBAmZZidvI6Fb2O","d608qFRoFHwbXd0Dap056i","d8HsitJHxOYqo801xBk8ev","daLLxC3KlGMZHpaB96xZVk","daocW8QktHYLAfd19h03eG","f7MxeJVDRPeZbX/PXcmj8f","f8lxlx1PlCyIFNrGDIw6r3","02delMVqdBD70a/HSD99FK","05ZSaGPWtMqKCYsLt5YuOh","06Vc5aQhlGS4Utnu1VQtxy","0apO9xoLpCeqAMhmO/3yGi","0b2Qh1E8JD86UtJ2sE6mu2","10I0hjuXxOmqAl7cVWrNiH","10M2pzlPRBsJmFrb9aSeHI","12WSAMRDZPBZxNNwf2of5s","1cYiofDjhM96mCn0flRzD7","2ami2ZmNpKY6TCtyJszSR7","33zumFnY5GfqsNCT1+Nagu","3bECfdcY5Mw7PEhUGqlyCt","50l6G8Ok5LIq0HYsaiAgwm","54m12iH8lL8KiYdqiEOtCV","57XQTnG4BFzLVvjNbQouS+","589b9xsLNBcYh4vxOmXWrm","5aXTKPIo1Ay5Si0xkeKBTX","5cO7kybDxGj4ipyMYdRYZB","5f5dyqtRNNxaFmVzYns6FZ","60W/opkbpLS7DdglAAe90R","69qNk9B5tO0LtU9nd5GJrk","6cfAM0h05I26mr6q0Ka91Q","6d/qEB6mZPWIaSo6VGMlq1","6eTu8pDHhAqqDk48LYeDJ7","74o5QWkBpIeattxCyes+YE","77Hys1NKRDDanlvE1FMWoU","7aXPefO3RIJZctPrfJRDrv","7ePr/KahNAU5P9XBbaUts+","87UvaLuTlIAZtWcg41U0Bs","8747A8NLNBC6uY7qexr3/N","89gD8ifphCU6Jc5kT32wvN","8bflKBPhtCqICjkrg/PWSJ","8f4ZA6OOZJcpqCt603YZfR","9bvaMerUlDyary99mJa6xp","a2MjXRFdtLlYQ5ouAFv/+R","a4amboegND+bTFdz8hzPvu","b1J/aAU2NKsKTB+tKz4WtA","b8rvvljRZI1akKeo2b+luX","cbs8qxK3NGl743IixBnYRk","d3t7MkXMZHoIuMSS+NWqMz","ddwacIeBtHTr5DO7HR9Q0t","e2xxboP05FZY8znF4m4iFR","ecpdLyjvZBwrvm+cedCcQy","f7Ec0syv5ELqwlKlhfhFgX"],"scenes":{},"redirect":[21,0,30,1,63,0],"deps":["internal","main"],"packs":{"027c85577":[38,39],"039a3cfc7":[34,46,18,64],"03a739372":[32,42,57],"03df09b57":[6,58],"050b7fa0c":[26,49,11,62],"06ef4c0ee":[25,29,37,5,59],"0c3be6657":[28,35,36,40,41,12],"0c682d633":[27,3,44,47,51,53],"0d61de7c8":[0,1,4,7,8,9,15,16,17,20],"0f195fbb2":[31,10,56,61],"0fb2571c3":[23,24,2,45,50,52],"0ffca7f66":[22,33,19]},"name":"PrefabsGame","importBase":"import","nativeBase":"native","debug":false,"isZip":false,"encrypted":false,"versions":{"import":["027c85577","c370b","039a3cfc7","82b1f","03a739372","c8cdb","03df09b57","30c6b","050b7fa0c","ca0d1","06ef4c0ee","856dc","0c3be6657","d8493","0c682d633","9a34e","0d61de7c8","c59b9","0f195fbb2","1b33b","0fb2571c3","d139c","0ffca7f66","6e622",43,"f4e3d",48,"00175",54,"95264",55,"43d76",13,"0448f",14,"62b28",60,"f31c8"],"native":[0,"87280",1,"fa09e",4,"6d707",7,"fc882",8,"f937e",9,"bdf84",15,"d55c2",16,"cdbc9",17,"306e8",20,"e686a"]}}